client/__init__.py
client/client.py
client/clients/__init__.py
client/clients/add_contact.py
client/clients/data_clients.py
client/clients/del_client.py
client/clients/main_window.py
client/clients/main_window_conv.py
client/clients/start_dialog.py
client/clients/transport.py
client/common/__init__.py
client/common/decos.py
client/common/descriptors.py
client/common/errors.py
client/common/metaclasses.py
client/common/utils.py
client/common/variables.py
mess_client_proj_2023-0.0.1.dist-info/METADATA
mess_client_proj_2023-0.0.1.dist-info/WHEEL
mess_client_proj_2023-0.0.1.dist-info/top_level.txt
mess_client_proj_2023-0.0.1.dist-info/RECORD
