Metadata-Version: 2.1
Name: mess-client-proj-2023
Version: 0.0.1
Summary: mess_client_proj_new
Author: Vyacheslav Lashin
Author-email: glory665@mail.ru
Requires-Dist: PyQt5
Requires-Dist: sqlalchemy
Requires-Dist: pycryptodome
Requires-Dist: pycryptodomex
